{"nodes": [{"id": "pages_calendar_calendar", "label": "Calendar page", "file_type": "code", "source_file": "src/pages/Calendar.tsx", "source_location": "70", "source_url": null, "captured_at": null, "author": null, "contributor": null}], "edges": [{"source": "pages_calendar_calendar", "target": "supabase_client_supabase", "relation": "calls", "confidence": "EXTRACTED", "confidence_score": 1.0, "source_file": "src/pages/Calendar.tsx", "source_location": "4", "weight": 1.0}, {"source": "pages_calendar_calendar", "target": "pages_index_coursecolor", "relation": "calls", "confidence": "EXTRACTED", "confidence_score": 1.0, "source_file": "src/pages/Calendar.tsx", "source_location": "24", "weight": 1.0}, {"source": "pages_calendar_calendar", "target": "supabase_types_table_calendar_entries", "relation": "shares_data_with", "confidence": "INFERRED", "confidence_score": 0.95, "source_file": "src/pages/Calendar.tsx", "source_location": "183", "weight": 1.0}, {"source": "pages_calendar_calendar", "target": "supabase_types_table_calendar_todos", "relation": "shares_data_with", "confidence": "INFERRED", "confidence_score": 0.95, "source_file": "src/pages/Calendar.tsx", "source_location": "204", "weight": 1.0}], "hyperedges": [{"id": "hyperedge_course_color_shared", "label": "courseColor exported from Index and consumed by Calendar, Shared", "nodes": ["pages_index_coursecolor", "pages_calendar_calendar", "pages_shared_shared"], "relation": "participate_in", "confidence": "EXTRACTED", "confidence_score": 1.0, "source_file": "src/pages/Calendar.tsx"}]}